[
  {
    "title": "Brand Archive",
    "url": "https://example.com/brand-archive",
    "desc": "브랜드 스토리와 제품 라인업을 한 화면에서 탐색할 수 있도록 설계한 아카이브형 웹사이트."
  },
  {
    "title": "Creator Dashboard",
    "url": "https://example.com/creator-dashboard",
    "desc": "콘텐츠 성과, 일정, 협업 요청을 빠르게 파악할 수 있도록 구성한 크리에이터 대시보드."
  },
  {
    "title": "City Guide Campaign",
    "url": "https://example.com/city-guide",
    "desc": "지역 행사와 장소 정보를 시각적으로 큐레이션한 프로모션 랜딩페이지."
  },
  {
    "title": "Studio Booking Flow",
    "url": "https://example.com/studio-booking",
    "desc": "촬영 스튜디오 예약 단계를 단순화하고 전환율을 높이는 데 초점을 둔 예약 플로우."
  },
  {
    "title": "Signal Commerce",
    "url": "https://example.com/signal-commerce",
    "desc": "상품 큐레이션과 빠른 결제 경험을 결합한 실험형 커머스 프로젝트."
  },
  {
    "title": "Live Event Microsite",
    "url": "https://example.com/live-event",
    "desc": "라이브 일정, 하이라이트, 티켓 링크를 집약해 보여주는 이벤트 마이크로사이트."
  }
]
